jobify/__init__.py
jobify/_internal/__init__.py
jobify/_internal/common/__init__.py
jobify/_internal/common/constants.py
jobify/_internal/common/datastructures.py
jobify/_internal/common/types.py
jobify/_internal/configuration.py
jobify/_internal/context.py
jobify/_internal/cron_parser.py
jobify/_internal/exceptions.py
jobify/_internal/inspection.py
jobify/_internal/message.py
jobify/_internal/middleware/__init__.py
jobify/_internal/middleware/base.py
jobify/_internal/middleware/exceptions.py
jobify/_internal/middleware/retry.py
jobify/_internal/middleware/timeout.py
jobify/_internal/router/__init__.py
jobify/_internal/router/base.py
jobify/_internal/router/node.py
jobify/_internal/router/root.py
jobify/_internal/runners.py
jobify/_internal/scheduler/__init__.py
jobify/_internal/scheduler/job.py
jobify/_internal/scheduler/misfire_policy.py
jobify/_internal/scheduler/scheduler.py
jobify/_internal/serializers/__init__.py
jobify/_internal/serializers/base.py
jobify/_internal/serializers/json.py
jobify/_internal/serializers/json_extended.py
jobify/_internal/serializers/pickle_unsafe.py
jobify/_internal/shared_state.py
jobify/_internal/storage/__init__.py
jobify/_internal/storage/abc.py
jobify/_internal/storage/dummy.py
jobify/_internal/storage/sqlite.py
jobify/_internal/typeadapter/__init__.py
jobify/_internal/typeadapter/base.py
jobify/_internal/typeadapter/dummy.py
jobify/crontab.py
jobify/exceptions/__init__.py
jobify/jobify.py
jobify/middleware/__init__.py
jobify/py.typed
jobify/router/__init__.py
jobify/serializers/__init__.py
jobify/storage/__init__.py
jobify-0.6.0.dist-info/WHEEL
jobify-0.6.0.dist-info/METADATA
jobify-0.6.0.dist-info/RECORD
