Metadata-Version: 2.4
Name: jobify
Version: 0.6.0
Summary: A modern, lightweight and robust task manager with a user-friendly interface and a wide range of features, using the low-level asyncio API and more.
Keywords: jobs,cron,asyncio,cron-jobs,scheduler,scheduling,asynchronous,job-scheduler,task-scheduler,python-scheduler,background-tasks,background-jobs,delayed-tasks
Author: Sergey Yavorsky
Author-email: Sergey Yavorsky <maclovi.dev@gmail.com>
License-Expression: MIT
Classifier: Typing :: Typed
Classifier: Framework :: Pytest
Classifier: Framework :: AsyncIO
Classifier: Natural Language :: English
Classifier: Development Status :: 4 - Beta
Classifier: Intended Audience :: Developers
Classifier: Operating System :: OS Independent
Classifier: License :: OSI Approved :: MIT License
Classifier: Programming Language :: Python :: 3
Classifier: Programming Language :: Python :: 3.10
Classifier: Programming Language :: Python :: 3.11
Classifier: Programming Language :: Python :: 3.12
Classifier: Programming Language :: Python :: 3.13
Classifier: Programming Language :: Python :: 3.14
Classifier: Topic :: Software Development :: Libraries :: Application Frameworks
Classifier: Topic :: Software Development :: Libraries :: Python Modules
Classifier: Topic :: Utilities
Requires-Dist: crontab==1.0.5
Requires-Dist: tzdata==2025.2 ; sys_platform == 'win32'
Requires-Dist: typing-extensions>=4.12.0
Requires-Python: >=3.10, <5
Project-URL: Homepage, https://theseriff.github.io/jobify/
Project-URL: Repository, https://github.com/theseriff/jobify
Project-URL: Documentation, https://theseriff.github.io/jobify/
Project-URL: Changelog, https://github.com/theseriff/jobify/blob/main/docs/CHANGELOG.md
Project-URL: Issues, https://github.com/theseriff/jobify/issues
